simple_exr/__init__.py
simple_exr/core.py
simple_exr-0.0.0.dist-info/licenses/LICENSE
simple_exr-0.0.0.dist-info/METADATA
simple_exr-0.0.0.dist-info/WHEEL
simple_exr-0.0.0.dist-info/top_level.txt
simple_exr-0.0.0.dist-info/RECORD
