Metadata-Version: 2.4
Name: simple_exr
Version: 0.0.0
Summary: A simple library for reading and writing EXR files
Author-email: NCJ <me@ncj.wiki>
License-Expression: MIT
Project-URL: homepage, https://github.com/iamNCJ/simple-exr
Classifier: Programming Language :: Python :: 3
Classifier: Operating System :: POSIX :: Linux
Classifier: Operating System :: MacOS
Requires-Python: >=3.8
License-File: LICENSE
Requires-Dist: OpenEXR>=3
Requires-Dist: numpy
Dynamic: license-file
